loclm/__init__.py
loclm/learner.py
loclm/models.py
loclm/q2sdata/test_set.json
loclm/q2sdata/training_set.json
loclm/q2smodel.json
loclm/query2sequence.py
loclm/s2qdata/test_set.json
loclm/s2qdata/train_set2.json
loclm/s2qdata/training_set.json
loclm/s2qmodel.json
loclm/sentence2query.py
loclm-0.1.3.dist-info/METADATA
loclm-0.1.3.dist-info/WHEEL
loclm-0.1.3.dist-info/RECORD
