Metadata-Version: 2.4
Name: loclm
Version: 0.1.3
Summary: localized language model specifically designed to be domain expert (instead of expert of everything) and very light weight
License: Custom
Author: Utkarsh (saraswat.utk@gmail.com)
Requires-Python: >=3.12
Classifier: License :: Other/Proprietary License
Classifier: Programming Language :: Python :: 3
Classifier: Programming Language :: Python :: 3.12
Classifier: Programming Language :: Python :: 3.13
Classifier: Programming Language :: Python :: 3.14
Requires-Dist: numpy (>=2.3.4,<3.0.0)
